get_nic/__init__.py
get_nic/getnic.py
get_nic-0.0.3.dist-info/LICENSE
get_nic-0.0.3.dist-info/METADATA
get_nic-0.0.3.dist-info/WHEEL
get_nic-0.0.3.dist-info/top_level.txt
get_nic-0.0.3.dist-info/RECORD
