Metadata-Version: 2.1
Name: get_nic
Version: 0.0.3
Summary: Get Network Interface details
Home-page: https://github.com/tech-novic/get-nic-details
Author: tech-novic
Author-email: pradish.purushottaman@outlook.com
License: UNKNOWN
Platform: UNKNOWN
Classifier: Programming Language :: Python :: 3
Classifier: Intended Audience :: Developers
Classifier: License :: OSI Approved :: MIT License
Classifier: Operating System :: POSIX :: Linux
